rohit_indian_states_25/__init__.py
rohit_indian_states_25/asgi.py
rohit_indian_states_25/settings.py
rohit_indian_states_25/urls.py
rohit_indian_states_25/wsgi.py
rst1/__init__.py
rst1/admin.py
rst1/apps.py
rst1/fields.py
rst1/forms.py
rst1/models.py
rst1/states.py
rst1/tests.py
rst1/views.py
rst1/migrations/__init__.py
rohit_indian_states_25-0.1.dist-info/METADATA
rohit_indian_states_25-0.1.dist-info/WHEEL
rohit_indian_states_25-0.1.dist-info/top_level.txt
rohit_indian_states_25-0.1.dist-info/RECORD
