Metadata-Version: 2.2
Name: rohit_indian_states_25
Version: 0.1
Summary: A Django app that provides Indian state choices as a model and form field.
Author: Rohit Joshi
Author-email: rohitjoshir.j.2000@gmail.com
License: MIT
Classifier: Framework :: Django
Classifier: Programming Language :: Python :: 3
Requires-Dist: django
Dynamic: author
Dynamic: author-email
Dynamic: classifier
Dynamic: license
Dynamic: requires-dist
Dynamic: summary
